vectorstore/__init__.py
vectorstore/vearch_cluster.py
vectorstore/vearch_old.py
intelligent_engine_core-0.1.0.dist-info/METADATA
intelligent_engine_core-0.1.0.dist-info/WHEEL
intelligent_engine_core-0.1.0.dist-info/RECORD
