Metadata-Version: 2.1
Name: intelligent-engine-core
Version: 0.1.0
Summary: 
Author: rag
Author-email: rag@jd.com
Requires-Python: >=3.9,<4.0
Classifier: Programming Language :: Python :: 3
Classifier: Programming Language :: Python :: 3.9
Classifier: Programming Language :: Python :: 3.10
Classifier: Programming Language :: Python :: 3.11
Classifier: Programming Language :: Python :: 3.12
Requires-Dist: aiohttp (>=3.10.6,<4.0.0)
Requires-Dist: httpx (>=0.27.2,<0.28.0)
Requires-Dist: langchain (>=0.3.1,<0.4.0)
Requires-Dist: langchain-core (>=0.3.6,<0.4.0)
Requires-Dist: langchain-openai (>=0.2.0,<0.3.0)
Requires-Dist: llama-index (>=0.11.14,<0.12.0)
Requires-Dist: llama-index-agent-openai (>=0.3.4,<0.4.0)
Requires-Dist: llama-index-core (>=0.11.14,<0.12.0)
Requires-Dist: python-dotenv (>=1.0.1,<2.0.0)
